quixote_docker/__init__.py
quixote_docker/docker_argument_parser.py
quixote_docker/docker_utils.py
quixote_docker/parse_shell.py
etna_quixote_docker-0.0.8.dist-info/METADATA
etna_quixote_docker-0.0.8.dist-info/WHEEL
etna_quixote_docker-0.0.8.dist-info/top_level.txt
etna_quixote_docker-0.0.8.dist-info/RECORD
