Metadata-Version: 2.1
Name: etna-quixote-docker
Version: 0.0.8
Summary: Addition to Quixote to deal with Docker
Home-page: https://github.com/etna-alternance/etna-quixote-docker
Author: Clément Doumergue
Author-email: clement.doumergue@etna.io
License: UNKNOWN
Platform: UNKNOWN
Classifier: Programming Language :: Python :: 3
Classifier: License :: OSI Approved :: MIT License
Classifier: Operating System :: OS Independent
Requires-Dist: bashlex
Requires-Dist: docker
